autofaker/__init__.py
autofaker/attributes.py
autofaker/autodata.py
autofaker/base.py
autofaker/builtins.py
autofaker/dataframe.py
autofaker/dates.py
autofaker/decorators.py
autofaker/enums.py
autofaker/factory.py
autofaker/fakes.py
autofaker/generator.py
autofaker/literals.py
autofaker-1.0.22.dist-info/licenses/LICENSE
autofaker-1.0.22.dist-info/METADATA
autofaker-1.0.22.dist-info/WHEEL
autofaker-1.0.22.dist-info/top_level.txt
autofaker-1.0.22.dist-info/RECORD
