Metadata-Version: 2.4
Name: autofaker
Version: 1.0.22
Summary: Python library designed to minimize the setup/arrange phase of your unit tests
Home-page: https://github.com/christianhelle/autofaker
Author: Christian Helle
Author-email: christian.helle@outlook.com
License: MIT License
Requires-Python: >=3.8
License-File: LICENSE
Requires-Dist: pandas
Requires-Dist: faker
Requires-Dist: typing_inspect
Dynamic: author
Dynamic: author-email
Dynamic: description
Dynamic: description-content-type
Dynamic: home-page
Dynamic: license
Dynamic: license-file
Dynamic: requires-dist
Dynamic: requires-python
Dynamic: summary
